setup.py
subparser/__init__.py
subparser/_version.py
subparser/subparser.py
subparser.egg-info/PKG-INFO
subparser.egg-info/SOURCES.txt
subparser.egg-info/dependency_links.txt
subparser.egg-info/requires.txt
subparser.egg-info/top_level.txt