Metadata-Version: 1.1
Name: subparser
Version: 0.2.0
Summary: utility class for handling argparse subparsers
Home-page: http://github.com/twang817/subparser
Author: Tommy Wang
Author-email: twang@august8.net
License: PSF
Download-URL: http://github.com/twang817/subparser/tarball/0.2.0
Platform: UNKNOWN
